[
  {
    "UniqueName": "CHD-CNG-GPOINT",
    "Station Wise Today  Sales": 0.0,
    "Date": "15-12-2025",
    "Time": "11:39:37 AM"
  },
  {
    "UniqueName": "CHD-CNG-JAAMFI",
    "Station Wise Today  Sales": 9.21875,
    "Date": "15-12-2025",
    "Time": "11:39:37 AM"
  },
  {
    "UniqueName": "CHD-CNG-JAIAMB",
    "Station Wise Today  Sales": 14.453125,
    "Date": "15-12-2025",
    "Time": "11:39:37 AM"
  },
  {
    "UniqueName": "CHD-CNG-MJMALO",
    "Station Wise Today  Sales": 0.0,
    "Date": "15-12-2025",
    "Time": "11:39:37 AM"
  },
  {
    "UniqueName": "CHD-CNG-SAMRUD",
    "Station Wise Today  Sales": 5.5,
    "Date": "15-12-2025",
    "Time": "11:39:37 AM"
  },
  {
    "UniqueName": "CHD-CNG-VMKOTI",
    "Station Wise Today  Sales": 4.140625,
    "Date": "15-12-2025",
    "Time": "11:39:37 AM"
  },
  {
    "UniqueName": "KRS-CNG-NUNNAX",
    "Station Wise Today  Sales": 6.15625,
    "Date": "15-12-2025",
    "Time": "11:39:37 AM"
  },
  {
    "UniqueName": "KRS-CNGI-VIJAYW",
    "Station Wise Today  Sales": 0.0,
    "Date": "15-12-2025",
    "Time": "11:39:37 AM"
  }
]