[
  {
    "UniqueName": "CHD-CNG-GPOINT",
    "Station Wise Today Sales": 13.46875,
    "Date": "17-12-2025",
    "Time": "12:52:38 PM"
  },
  {
    "UniqueName": "CHD-CNG-JAAMFI",
    "Station Wise Today Sales": 238.09375,
    "Date": "17-12-2025",
    "Time": "12:52:38 PM"
  },
  {
    "UniqueName": "CHD-CNG-JAIAMB",
    "Station Wise Today Sales": 246.25,
    "Date": "17-12-2025",
    "Time": "12:52:38 PM"
  },
  {
    "UniqueName": "CHD-CNG-VMKOTI",
    "Station Wise Today Sales": 254.2890625,
    "Date": "17-12-2025",
    "Time": "12:52:38 PM"
  },
  {
    "UniqueName": "KRS-CGS-AGRIPA",
    "Station Wise Today Sales": 37.578125,
    "Date": "17-12-2025",
    "Time": "12:52:38 PM"
  },
  {
    "UniqueName": "KRS-CGS-YANAMA",
    "Station Wise Today Sales": 89.46875,
    "Date": "17-12-2025",
    "Time": "12:52:38 PM"
  },
  {
    "UniqueName": "KRS-CNG-AKSHAY",
    "Station Wise Today Sales": 150.5546875,
    "Date": "17-12-2025",
    "Time": "12:52:38 PM"
  },
  {
    "UniqueName": "KRS-CNG-DODOMA",
    "Station Wise Today Sales": 288.890625,
    "Date": "17-12-2025",
    "Time": "12:52:38 PM"
  },
  {
    "UniqueName": "KRS-CNG-HIMAJA",
    "Station Wise Today Sales": 362.8125,
    "Date": "17-12-2025",
    "Time": "12:52:38 PM"
  },
  {
    "UniqueName": "KRS-CNG-KANCHI",
    "Station Wise Today Sales": 100.125,
    "Date": "17-12-2025",
    "Time": "12:52:38 PM"
  },
  {
    "UniqueName": "KRS-CNG-MARUTH",
    "Station Wise Today Sales": 464.71875,
    "Date": "17-12-2025",
    "Time": "12:52:38 PM"
  },
  {
    "UniqueName": "KRS-CNG-NUNNAX",
    "Station Wise Today Sales": 138.515625,
    "Date": "17-12-2025",
    "Time": "12:52:38 PM"
  },
  {
    "UniqueName": "KRS-CNG-PARITA",
    "Station Wise Today Sales": 95.40625,
    "Date": "17-12-2025",
    "Time": "12:52:38 PM"
  },
  {
    "UniqueName": "KRS-CNG-PAVANS",
    "Station Wise Today Sales": 296.75,
    "Date": "17-12-2025",
    "Time": "12:52:38 PM"
  },
  {
    "UniqueName": "KRS-CNGI-GULABC",
    "Station Wise Today Sales": 74.875,
    "Date": "17-12-2025",
    "Time": "12:52:38 PM"
  },
  {
    "UniqueName": "KRS-CNGI-KANURU",
    "Station Wise Today Sales": 131.8125,
    "Date": "17-12-2025",
    "Time": "12:52:38 PM"
  },
  {
    "UniqueName": "KRS-CNGI-RAHMAN",
    "Station Wise Today Sales": 92.28125,
    "Date": "17-12-2025",
    "Time": "12:52:38 PM"
  },
  {
    "UniqueName": "KRS-CNGI-SAIROA",
    "Station Wise Today Sales": 159.03125,
    "Date": "17-12-2025",
    "Time": "12:52:38 PM"
  },
  {
    "UniqueName": "KRS-CNGI-SRIRAM",
    "Station Wise Today Sales": 192.8125,
    "Date": "17-12-2025",
    "Time": "12:52:38 PM"
  },
  {
    "UniqueName": "KRS-CNGI-SRIRAV",
    "Station Wise Today Sales": 201.85999999998603,
    "Date": "17-12-2025",
    "Time": "12:52:38 PM"
  },
  {
    "UniqueName": "KRS-CNGI-SRISAI",
    "Station Wise Today Sales": 40.3828125,
    "Date": "17-12-2025",
    "Time": "12:52:38 PM"
  },
  {
    "UniqueName": "KRS-CNGI-SVKFIL",
    "Station Wise Today Sales": 111.84375,
    "Date": "17-12-2025",
    "Time": "12:52:38 PM"
  }
]